{"provides":{"GraphViz2::Parse::Regexp":{"file":"lib/GraphViz2/Parse/Regexp.pm","version":"2.47"},"GraphViz2":{"version":"2.57","file":"lib/GraphViz2.pm"},"GraphViz2::Parse::Yacc":{"version":"2.47","file":"lib/GraphViz2/Parse/Yacc.pm"},"GraphViz2::Parse::Yapp":{"file":"lib/GraphViz2/Parse/Yapp.pm","version":"2.47"},"GraphViz2::Parse::STT":{"version":"2.47","file":"lib/GraphViz2/Parse/STT.pm"}},"pathname":"E/ET/ETJ/GraphViz2-2.57.tar.gz","target":"E/ET/ETJ/GraphViz2-2.57.tar.gz","version":"2.57","name":"GraphViz2","dist":"GraphViz2-2.57"}