{"dist":"Config-Crontab-1.45","target":"Config::Crontab","name":"Config::Crontab","provides":{"Config::Crontab::Comment":{"file":"Crontab.pm","version":"1.45"},"Config::Crontab::Env":{"version":"1.45","file":"Crontab.pm"},"Config::Crontab::Event":{"file":"Crontab.pm","version":"1.45"},"Config::Crontab::Container":{"version":"1.45","file":"Crontab.pm"},"Config::Crontab::Base":{"version":"1.45","file":"Crontab.pm"},"Config::Crontab::Block":{"file":"Crontab.pm","version":"1.45"},"Config::Crontab":{"file":"Crontab.pm","version":"1.45"}},"pathname":"S/SC/SCOTTW/Config-Crontab-1.45.tar.gz","version":"1.45"}