{"target":"C/CO/CORION/Spreadsheet-ReadSXC-0.29.tar.gz","version":"0.29","name":"Spreadsheet::ReadSXC","provides":{"Spreadsheet::ParseODS":{"version":"0.29","file":"lib/Spreadsheet/ParseODS.pm"},"Spreadsheet::ParseODS::Cell":{"version":"0.29","file":"lib/Spreadsheet/ParseODS/Cell.pm"},"Spreadsheet::ReadSXC":{"version":"0.29","file":"lib/Spreadsheet/ReadSXC.pm"},"Spreadsheet::ParseODS::Workbook":{"version":"0.29","file":"lib/Spreadsheet/ParseODS/Workbook.pm"},"Spreadsheet::ParseODS::Worksheet":{"version":"0.29","file":"lib/Spreadsheet/ParseODS/Worksheet.pm"},"Spreadsheet::ParseODS::Settings":{"version":"0.29","file":"lib/Spreadsheet/ParseODS/Settings.pm"},"Spreadsheet::ParseODS::Styles":{"file":"lib/Spreadsheet/ParseODS/Styles.pm","version":"0.29"}},"dist":"Spreadsheet-ReadSXC-0.29","pathname":"C/CO/CORION/Spreadsheet-ReadSXC-0.29.tar.gz"}