{"provides":{"Spreadsheet::ParseXLSX::Decryptor::Standard":{"version":"0.27","file":"lib/Spreadsheet/ParseXLSX/Decryptor/Standard.pm"},"Spreadsheet::ParseXLSX::Decryptor":{"version":"0.27","file":"lib/Spreadsheet/ParseXLSX/Decryptor.pm"},"Spreadsheet::ParseXLSX":{"file":"lib/Spreadsheet/ParseXLSX.pm","version":"0.27"},"Spreadsheet::ParseXLSX::Decryptor::Agile":{"file":"lib/Spreadsheet/ParseXLSX/Decryptor/Agile.pm","version":"0.27"}},"version":"0.27","target":"Spreadsheet::ParseXLSX","dist":"Spreadsheet-ParseXLSX-0.27","pathname":"D/DO/DOY/Spreadsheet-ParseXLSX-0.27.tar.gz","name":"Spreadsheet::ParseXLSX"}